MANIFEST.in
README.md
setup.py
nb2mail/__init__.py
nb2mail_unify.egg-info/PKG-INFO
nb2mail_unify.egg-info/SOURCES.txt
nb2mail_unify.egg-info/dependency_links.txt
nb2mail_unify.egg-info/entry_points.txt
nb2mail_unify.egg-info/not-zip-safe
nb2mail_unify.egg-info/requires.txt
nb2mail_unify.egg-info/top_level.txt